LICENSE
MANIFEST.in
README.rst
setup.cfg
setup.py
django_oscar_eurotaxes.egg-info/PKG-INFO
django_oscar_eurotaxes.egg-info/SOURCES.txt
django_oscar_eurotaxes.egg-info/dependency_links.txt
django_oscar_eurotaxes.egg-info/requires.txt
django_oscar_eurotaxes.egg-info/top_level.txt
eurotaxes/__init__.py
eurotaxes/__init__.pyc
eurotaxes/catalogue/__init__.py
eurotaxes/catalogue/admin.py
eurotaxes/catalogue/config.py
eurotaxes/catalogue/models.py
eurotaxes/catalogue/migrations/0001_initial.py
eurotaxes/catalogue/migrations/0002_auto_20150217_1221.py
eurotaxes/catalogue/migrations/0003_data_migration_slugs.py
eurotaxes/catalogue/migrations/0004_auto_20150217_1710.py
eurotaxes/catalogue/migrations/0005_auto_20150604_1450.py
eurotaxes/catalogue/migrations/0006_auto_20150907_1556.py
eurotaxes/catalogue/migrations/__init__.py
eurotaxes/dashboard/__init__.py
eurotaxes/dashboard/config.py
eurotaxes/dashboard/models.py
eurotaxes/dashboard/catalogue/__init__.py
eurotaxes/dashboard/catalogue/config.py
eurotaxes/dashboard/catalogue/forms.py
eurotaxes/dashboard/catalogue/models.py
eurotaxes/partner/__init__.py
eurotaxes/partner/admin.py
eurotaxes/partner/config.py
eurotaxes/partner/managers.py
eurotaxes/partner/models.py
eurotaxes/partner/strategy.py
eurotaxes/partner/management/__init__.py
eurotaxes/partner/management/commands/__init__.py
eurotaxes/partner/management/commands/oscar_populate_taxes.py
eurotaxes/partner/migrations/0001_initial.py
eurotaxes/partner/migrations/0002_auto_20141007_2032.py
eurotaxes/partner/migrations/0003_auto_20150604_1450.py
eurotaxes/partner/migrations/0004_vatcountry.py
eurotaxes/partner/migrations/0005_auto_20150907_1555.py
eurotaxes/partner/migrations/0006_auto_20150907_1602.py
eurotaxes/partner/migrations/__init__.py