Metadata-Version: 1.1
Name: django-oscar-eurotaxes
Version: 0.2.1
Summary: Package to manage taxes with django-oscar if the company must accomplish the European Laws of Taxes
Home-page: https://bitbucket.org/abalt/django-oscar-eurotaxes
Author: Abalt
Author-email: admin@abalt.org
License: Copyright (c) 2011, Tangent Communications PLC and individual contributors.
